agent_ledger/__init__.py
agent_ledger/errors.py
agent_ledger/ledger.py
agent_ledger/observability.py
agent_ledger/py.typed
agent_ledger/types.py
agent_ledger/utils.py
agent_ledger/stores/__init__.py
agent_ledger/stores/base.py
agent_ledger/stores/memory.py
agent_ledger/stores/postgres.py
agent_ledger-0.2.0.dist-info/METADATA
agent_ledger-0.2.0.dist-info/WHEEL
agent_ledger-0.2.0.dist-info/licenses/LICENSE
agent_ledger-0.2.0.dist-info/RECORD
