Metadata-Version: 2.4
Name: agent-ledger
Version: 0.2.0
Summary: Idempotency and audit ledger for AI agent tool calls
Project-URL: Homepage, https://github.com/rune0/agent-ledger-py
Project-URL: Documentation, https://github.com/rune0/agent-ledger-py#readme
Project-URL: Repository, https://github.com/rune0/agent-ledger-py
Project-URL: Issues, https://github.com/rune0/agent-ledger-py/issues
Author-email: Rune0 <rune0org@gmail.com>
License-Expression: Apache-2.0
License-File: LICENSE
Keywords: ai-agents,approvals,audit,governance,hitl,human-in-the-loop,idempotency,ledger,tool-calls
Classifier: Development Status :: 4 - Beta
Classifier: Framework :: AsyncIO
Classifier: Intended Audience :: Developers
Classifier: License :: OSI Approved :: Apache Software License
Classifier: Programming Language :: Python :: 3
Classifier: Programming Language :: Python :: 3.10
Classifier: Programming Language :: Python :: 3.11
Classifier: Programming Language :: Python :: 3.12
Classifier: Programming Language :: Python :: 3.13
Classifier: Typing :: Typed
Requires-Python: >=3.10
Requires-Dist: cachetools>=5.3.0
Requires-Dist: pydantic>=2.0.0
Requires-Dist: rfc8785>=0.1.2
Provides-Extra: all
Requires-Dist: mypy>=1.9.0; extra == 'all'
Requires-Dist: psycopg[binary,pool]>=3.1.0; extra == 'all'
Requires-Dist: pytest-asyncio>=0.23.0; extra == 'all'
Requires-Dist: pytest-cov>=4.0.0; extra == 'all'
Requires-Dist: pytest>=8.0.0; extra == 'all'
Requires-Dist: ruff>=0.4.0; extra == 'all'
Provides-Extra: asyncpg
Requires-Dist: asyncpg>=0.29.0; extra == 'asyncpg'
Provides-Extra: dev
Requires-Dist: mypy>=1.9.0; extra == 'dev'
Requires-Dist: pytest-asyncio>=0.23.0; extra == 'dev'
Requires-Dist: pytest-cov>=4.0.0; extra == 'dev'
Requires-Dist: pytest>=8.0.0; extra == 'dev'
Requires-Dist: ruff>=0.4.0; extra == 'dev'
Provides-Extra: otel
Requires-Dist: opentelemetry-api>=1.20.0; extra == 'otel'
Provides-Extra: postgres
Requires-Dist: psycopg[binary,pool]>=3.1.0; extra == 'postgres'
